tep/__init__.py
tep/cli.py
tep/config.py
tep/file.py
tep/har.py
tep/patch/__init__.py
tep/patch/patch_json.py
tep/patch/patch_logging.py
tep/patch/patch_pymysql.py
tep/patch/patch_random.py
tep/patch/patch_requests.py
tep/patch/patch_str.py
tep/patch/patch_time.py
tep/patch/patch_uuid.py
tep/plugin.py
tep/run.py
tep/scaffold.py
tep/static/app.js
tep/static/index.jinja2
tep/static/style.css
tep/step.py
tep/utils/__init__.py
tep/utils/pairwise.py
tep/variable.py
tep-3.0.6.dist-info/LICENSE
tep-3.0.6.dist-info/METADATA
tep-3.0.6.dist-info/WHEEL
tep-3.0.6.dist-info/entry_points.txt
tep-3.0.6.dist-info/RECORD
