Metadata-Version: 2.1
Name: tep
Version: 3.0.6
Summary: tep is a testing framework to help you write pytest more easily. Try Easy Pytest!
Home-page: https://github.com/dongfanger/tep
License: Apache-2.0
Keywords: testing,http,framework,pytest
Author: dongfanger
Author-email: dongfanger@outlook.com
Requires-Python: >=3.8,<4.0
Classifier: License :: OSI Approved :: Apache Software License
Classifier: Operating System :: MacOS
Classifier: Operating System :: Microsoft :: Windows
Classifier: Operating System :: POSIX :: Linux
Classifier: Programming Language :: Python :: 3
Classifier: Programming Language :: Python :: 3.8
Classifier: Programming Language :: Python :: 3.9
Classifier: Programming Language :: Python :: 3.10
Classifier: Programming Language :: Python :: 3.11
Classifier: Programming Language :: Python :: 3.12
Classifier: Programming Language :: Python :: 3.13
Classifier: Topic :: Software Development :: Libraries :: Python Modules
Classifier: Topic :: Software Development :: Quality Assurance
Classifier: Topic :: Software Development :: Testing
Requires-Dist: allpairspy (>=2.5.1,<3.0.0)
Requires-Dist: deepdiff (>=6.7.1,<7.0.0)
Requires-Dist: faker (>=4.1.1,<5.0.0)
Requires-Dist: filelock (>=3.8.2,<4.0.0)
Requires-Dist: haralyzer (>=2.4.0,<3.0.0)
Requires-Dist: httpx (>=0.25.1,<0.26.0)
Requires-Dist: jsonpath (>=0.82,<0.83)
Requires-Dist: pydantic (>=1.9.0,<2.0.0)
Requires-Dist: pymysql (>=1.1.0,<2.0.0)
Requires-Dist: pytest (>=7.1.1,<8.0.0)
Requires-Dist: pytest-assume (>=2.4.2,<3.0.0)
Requires-Dist: pytest-html (>=4.0.2,<5.0.0)
Requires-Dist: pytest-xdist (>=3.1.0,<4.0.0)
Requires-Dist: pyyaml (>=6.0.1,<7.0.0)
Requires-Dist: requests (>=2.22.0,<3.0.0)
Requires-Dist: tenacity (>=8.2.3,<9.0.0)
Requires-Dist: urllib3 (>=2.2.3,<3.0.0)
Project-URL: Repository, https://github.com/dongfanger/tep
